[
  {
    "id": "760510",
    "stage": "quarterfinals",
    "group": "Quarterfinals",
    "kickoffUtc": "2026-07-09T20:00Z",
    "kickoffTaiwan": "2026-07-10T04:00:00+08:00",
    "venue": "Gillette Stadium",
    "city": "Foxborough, Massachusetts",
    "status": "Scheduled",
    "completed": false,
    "home": {
      "id": "19282",
      "name": "Round of 16 1 Winner",
      "zhName": "Round of 16 1 Winner",
      "shortName": "RD16 W1",
      "abbr": "RD16 W1",
      "logo": "",
      "homeAway": "home",
      "score": "0",
      "winner": false
    },
    "away": {
      "id": "2869",
      "name": "Morocco",
      "zhName": "摩洛哥",
      "shortName": "Morocco",
      "abbr": "MAR",
      "logo": "https://a.espncdn.com/i/teamlogos/countries/500/mar.png",
      "homeAway": "away",
      "score": "0",
      "winner": false
    },
    "probabilities": null
  }
]
